{
  "name": "Erard Concert Harp",
  "source": "https://harpcanada.com/harpmaking/erard.htm",
  "num_strings": 47,
  "units": {
    "length": "mm",
    "diameter": "mm",
    "tension": "N",
    "frequency": "Hz",
    "spacing": "mm"
  },
  "string_spacing": {
    "type": "edge-to-edge",
    "gap": 14.0
  },
  "coordinate_system": {
    "description": "C1 at origin, strings spaced along X axis, string length along Z axis",
    "x_axis": "string positions with 14.0mm finger gap (C1=0, G7=699.8mm)",
    "z_axis": "string length (soundboard to tuning pin)"
  },
  "strings": [
    {
      "num": 1,
      "note": "C1",
      "freq": 32.7,
      "length": 1514.93,
      "x_pos": 0.0,
      "core_material": "steel",
      "wire_material": "bronze",
      "core_dia": 0.66,
      "wire_dia": 0.508,
      "tension": 234.43,
      "total_dia": 1.6760000000000002
    },
    {
      "num": 2,
      "note": "D1",
      "freq": 36.71,
      "length": 1489.68,
      "x_pos": 15.574000000000002,
      "core_material": "steel",
      "wire_material": "bronze",
      "core_dia": 0.66,
      "wire_dia": 0.406,
      "tension": 226.84,
      "total_dia": 1.472
    },
    {
      "num": 3,
      "note": "E1",
      "freq": 41.2,
      "length": 1464.44,
      "x_pos": 30.945000000000004,
      "core_material": "steel",
      "wire_material": "bronze",
      "core_dia": 0.61,
      "wire_dia": 0.33,
      "tension": 218.25,
      "total_dia": 1.27
    },
    {
      "num": 4,
      "note": "F1",
      "freq": 43.65,
      "length": 1439.19,
      "x_pos": 46.215,
      "core_material": "steel",
      "wire_material": "bronze",
      "core_dia": 0.61,
      "wire_dia": 0.33,
      "tension": 217.39,
      "total_dia": 1.27
    },
    {
      "num": 5,
      "note": "G1",
      "freq": 49.0,
      "length": 1408.89,
      "x_pos": 61.4595,
      "core_material": "steel",
      "wire_material": "bronze",
      "core_dia": 0.559,
      "wire_dia": 0.33,
      "tension": 226.16,
      "total_dia": 1.219
    },
    {
      "num": 6,
      "note": "A1",
      "freq": 55.0,
      "length": 1378.58,
      "x_pos": 76.67849999999999,
      "core_material": "steel",
      "wire_material": "bronze",
      "core_dia": 0.559,
      "wire_dia": 0.33,
      "tension": 236.76,
      "total_dia": 1.219
    },
    {
      "num": 7,
      "note": "B1",
      "freq": 61.74,
      "length": 1348.28,
      "x_pos": 91.79599999999998,
      "core_material": "steel",
      "wire_material": "bronze",
      "core_dia": 0.508,
      "wire_dia": 0.254,
      "tension": 226.34,
      "total_dia": 1.016
    },
    {
      "num": 8,
      "note": "C2",
      "freq": 65.41,
      "length": 1317.98,
      "x_pos": 106.81199999999997,
      "core_material": "steel",
      "wire_material": "bronze",
      "core_dia": 0.508,
      "wire_dia": 0.254,
      "tension": 222.14,
      "total_dia": 1.016
    },
    {
      "num": 9,
      "note": "D2",
      "freq": 73.42,
      "length": 1282.62,
      "x_pos": 121.77699999999996,
      "core_material": "steel",
      "wire_material": "bronze",
      "core_dia": 0.508,
      "wire_dia": 0.203,
      "tension": 217.25,
      "total_dia": 0.914
    },
    {
      "num": 10,
      "note": "E2",
      "freq": 82.41,
      "length": 1242.24,
      "x_pos": 137.55499999999995,
      "core_material": "nylon",
      "wire_material": "nylon",
      "core_dia": 1.524,
      "wire_dia": 0.559,
      "tension": 210.07,
      "total_dia": 2.6420000000000003
    },
    {
      "num": 11,
      "note": "F2",
      "freq": 87.31,
      "length": 1222.04,
      "x_pos": 154.14599999999996,
      "core_material": "nylon",
      "wire_material": "nylon",
      "core_dia": 1.524,
      "wire_dia": 0.508,
      "tension": 212.41,
      "total_dia": 2.54
    },
    {
      "num": 12,
      "note": "G2",
      "freq": 97.99,
      "length": 1186.69,
      "x_pos": 170.58399999999997,
      "core_material": "nylon",
      "wire_material": "nylon",
      "core_dia": 1.524,
      "wire_dia": 0.406,
      "tension": 217.01,
      "total_dia": 2.3360000000000003
    },
    {
      "num": 13,
      "note": "A2",
      "freq": 110.0,
      "length": 1110.95,
      "x_pos": 186.844,
      "core_material": "nylon",
      "wire_material": "nylon",
      "core_dia": 1.524,
      "wire_dia": 0.33,
      "tension": 212.57,
      "total_dia": 2.184
    },
    {
      "num": 14,
      "note": "B2",
      "freq": 123.47,
      "length": 1055.4,
      "x_pos": 202.96450000000002,
      "core_material": "nylon",
      "wire_material": "nylon",
      "core_dia": 1.397,
      "wire_dia": 0.33,
      "tension": 213.09,
      "total_dia": 2.057
    },
    {
      "num": 15,
      "note": "C3",
      "freq": 130.81,
      "length": 989.76,
      "x_pos": 219.02150000000003,
      "core_material": "nylon",
      "wire_material": "nylon",
      "core_dia": 1.397,
      "wire_dia": 0.33,
      "tension": 210.36,
      "total_dia": 2.057
    },
    {
      "num": 16,
      "note": "D3",
      "freq": 146.83,
      "length": 924.1,
      "x_pos": 235.01500000000004,
      "core_material": "nylon",
      "wire_material": "nylon",
      "core_dia": 1.27,
      "wire_dia": 0.33,
      "tension": 202.01,
      "total_dia": 1.9300000000000002
    },
    {
      "num": 17,
      "note": "E3",
      "freq": 164.81,
      "length": 863.5,
      "x_pos": 250.81800000000004,
      "core_material": "nylon",
      "wire_material": "nylon",
      "core_dia": 1.27,
      "wire_dia": 0.203,
      "tension": 173.35,
      "total_dia": 1.6760000000000002
    },
    {
      "num": 18,
      "note": "F3",
      "freq": 174.61,
      "length": 792.81,
      "x_pos": 266.4940000000001,
      "core_material": "nylon",
      "wire_material": "nylon",
      "core_dia": 1.27,
      "wire_dia": 0.203,
      "tension": 164.04,
      "total_dia": 1.6760000000000002
    },
    {
      "num": 19,
      "note": "G3",
      "freq": 196.0,
      "length": 732.21,
      "x_pos": 282.1065000000001,
      "core_material": "nylon",
      "wire_material": "nylon",
      "core_dia": 1.143,
      "wire_dia": 0.203,
      "tension": 149.55,
      "total_dia": 1.549
    },
    {
      "num": 20,
      "note": "A3",
      "freq": 220.0,
      "length": 666.57,
      "x_pos": 297.6555000000001,
      "core_material": "nylon",
      "wire_material": "nylon",
      "core_dia": 1.143,
      "wire_dia": 0.203,
      "tension": 156.15,
      "total_dia": 1.549
    },
    {
      "num": 21,
      "note": "B3",
      "freq": 246.94,
      "length": 621.13,
      "x_pos": 313.06500000000005,
      "core_material": "nylon",
      "wire_material": null,
      "core_dia": 1.27,
      "wire_dia": null,
      "tension": 127.21,
      "total_dia": 1.27
    },
    {
      "num": 22,
      "note": "C4",
      "freq": 261.63,
      "length": 570.61,
      "x_pos": 328.33500000000004,
      "core_material": "nylon",
      "wire_material": null,
      "core_dia": 1.27,
      "wire_dia": null,
      "tension": 120.51,
      "total_dia": 1.27
    },
    {
      "num": 23,
      "note": "D4",
      "freq": 293.66,
      "length": 525.17,
      "x_pos": 343.605,
      "core_material": "nylon",
      "wire_material": null,
      "core_dia": 1.27,
      "wire_dia": null,
      "tension": 128.61,
      "total_dia": 1.27
    },
    {
      "num": 24,
      "note": "E4",
      "freq": 329.63,
      "length": 484.78,
      "x_pos": 358.8115,
      "core_material": "nylon",
      "wire_material": null,
      "core_dia": 1.143,
      "wire_dia": null,
      "tension": 111.85,
      "total_dia": 1.143
    },
    {
      "num": 25,
      "note": "F4",
      "freq": 349.23,
      "length": 449.43,
      "x_pos": 373.95450000000005,
      "core_material": "nylon",
      "wire_material": null,
      "core_dia": 1.143,
      "wire_dia": null,
      "tension": 107.91,
      "total_dia": 1.143
    },
    {
      "num": 26,
      "note": "G4",
      "freq": 392.0,
      "length": 414.07,
      "x_pos": 389.0975000000001,
      "core_material": "nylon",
      "wire_material": null,
      "core_dia": 1.143,
      "wire_dia": null,
      "tension": 115.4,
      "total_dia": 1.143
    },
    {
      "num": 27,
      "note": "A4",
      "freq": 440.0,
      "length": 383.77,
      "x_pos": 404.1770000000001,
      "core_material": "nylon",
      "wire_material": null,
      "core_dia": 1.016,
      "wire_dia": null,
      "tension": 98.68,
      "total_dia": 1.016
    },
    {
      "num": 28,
      "note": "B4",
      "freq": 493.88,
      "length": 353.49,
      "x_pos": 419.19300000000004,
      "core_material": "nylon",
      "wire_material": null,
      "core_dia": 1.016,
      "wire_dia": null,
      "tension": 105.48,
      "total_dia": 1.016
    },
    {
      "num": 29,
      "note": "C5",
      "freq": 523.25,
      "length": 328.24,
      "x_pos": 434.209,
      "core_material": "nylon",
      "wire_material": null,
      "core_dia": 1.016,
      "wire_dia": null,
      "tension": 102.09,
      "total_dia": 1.016
    },
    {
      "num": 30,
      "note": "D5",
      "freq": 587.33,
      "length": 303.0,
      "x_pos": 449.174,
      "core_material": "nylon",
      "wire_material": null,
      "core_dia": 0.914,
      "wire_dia": null,
      "tension": 88.78,
      "total_dia": 0.914
    },
    {
      "num": 31,
      "note": "E5",
      "freq": 659.26,
      "length": 277.72,
      "x_pos": 464.08799999999997,
      "core_material": "nylon",
      "wire_material": null,
      "core_dia": 0.914,
      "wire_dia": null,
      "tension": 93.99,
      "total_dia": 0.914
    },
    {
      "num": 32,
      "note": "F5",
      "freq": 698.46,
      "length": 262.58,
      "x_pos": 479.00199999999995,
      "core_material": "nylon",
      "wire_material": null,
      "core_dia": 0.914,
      "wire_dia": null,
      "tension": 94.27,
      "total_dia": 0.914
    },
    {
      "num": 33,
      "note": "G5",
      "freq": 783.99,
      "length": 237.34,
      "x_pos": 493.91599999999994,
      "core_material": "nylon",
      "wire_material": null,
      "core_dia": 0.914,
      "wire_dia": null,
      "tension": 97.04,
      "total_dia": 0.914
    },
    {
      "num": 34,
      "note": "A5",
      "freq": 880.0,
      "length": 222.2,
      "x_pos": 508.7794999999999,
      "core_material": "nylon",
      "wire_material": null,
      "core_dia": 0.813,
      "wire_dia": null,
      "tension": 84.69,
      "total_dia": 0.813
    },
    {
      "num": 35,
      "note": "B5",
      "freq": 987.77,
      "length": 207.04,
      "x_pos": 523.5925,
      "core_material": "nylon",
      "wire_material": null,
      "core_dia": 0.813,
      "wire_dia": null,
      "tension": 92.63,
      "total_dia": 0.813
    },
    {
      "num": 36,
      "note": "C6",
      "freq": 1046.5,
      "length": 191.9,
      "x_pos": 538.4055000000001,
      "core_material": "nylon",
      "wire_material": null,
      "core_dia": 0.813,
      "wire_dia": null,
      "tension": 89.32,
      "total_dia": 0.813
    },
    {
      "num": 37,
      "note": "D6",
      "freq": 1174.7,
      "length": 176.73,
      "x_pos": 553.1930000000001,
      "core_material": "nylon",
      "wire_material": null,
      "core_dia": 0.762,
      "wire_dia": null,
      "tension": 83.9,
      "total_dia": 0.762
    },
    {
      "num": 38,
      "note": "E6",
      "freq": 1318.5,
      "length": 161.59,
      "x_pos": 567.9295000000001,
      "core_material": "nylon",
      "wire_material": null,
      "core_dia": 0.711,
      "wire_dia": null,
      "tension": 76.98,
      "total_dia": 0.711
    },
    {
      "num": 39,
      "note": "F6",
      "freq": 1396.9,
      "length": 146.43,
      "x_pos": 582.6405000000001,
      "core_material": "nylon",
      "wire_material": null,
      "core_dia": 0.711,
      "wire_dia": null,
      "tension": 70.94,
      "total_dia": 0.711
    },
    {
      "num": 40,
      "note": "G6",
      "freq": 1568.0,
      "length": 131.29,
      "x_pos": 597.3515000000001,
      "core_material": "nylon",
      "wire_material": null,
      "core_dia": 0.711,
      "wire_dia": null,
      "tension": 71.86,
      "total_dia": 0.711
    },
    {
      "num": 41,
      "note": "A6",
      "freq": 1760.0,
      "length": 121.18,
      "x_pos": 612.0245000000001,
      "core_material": "nylon",
      "wire_material": null,
      "core_dia": 0.635,
      "wire_dia": null,
      "tension": 61.49,
      "total_dia": 0.635
    },
    {
      "num": 42,
      "note": "B6",
      "freq": 1975.5,
      "length": 111.1,
      "x_pos": 626.6595000000001,
      "core_material": "nylon",
      "wire_material": null,
      "core_dia": 0.635,
      "wire_dia": null,
      "tension": 65.12,
      "total_dia": 0.635
    },
    {
      "num": 43,
      "note": "C7",
      "freq": 2093.0,
      "length": 100.99,
      "x_pos": 641.2945000000001,
      "core_material": "nylon",
      "wire_material": null,
      "core_dia": 0.635,
      "wire_dia": null,
      "tension": 60.39,
      "total_dia": 0.635
    },
    {
      "num": 44,
      "note": "D7",
      "freq": 2349.3,
      "length": 90.91,
      "x_pos": 655.9295000000001,
      "core_material": "nylon",
      "wire_material": null,
      "core_dia": 0.635,
      "wire_dia": null,
      "tension": 61.66,
      "total_dia": 0.635
    },
    {
      "num": 45,
      "note": "E7",
      "freq": 2637.0,
      "length": 80.8,
      "x_pos": 670.5645000000001,
      "core_material": "nylon",
      "wire_material": null,
      "core_dia": 0.635,
      "wire_dia": null,
      "tension": 61.37,
      "total_dia": 0.635
    },
    {
      "num": 46,
      "note": "F7",
      "freq": 2793.8,
      "length": 70.69,
      "x_pos": 685.1995000000001,
      "core_material": "nylon",
      "wire_material": null,
      "core_dia": 0.635,
      "wire_dia": null,
      "tension": 52.72,
      "total_dia": 0.635
    },
    {
      "num": 47,
      "note": "G7",
      "freq": 3136.0,
      "length": 60.6,
      "x_pos": 699.8345,
      "core_material": "nylon",
      "wire_material": null,
      "core_dia": 0.635,
      "wire_dia": null,
      "tension": 48.83,
      "total_dia": 0.635
    }
  ]
}